giting/__init__.py
giting/__version__.py
giting/cli.py
giting/core/__init__.py
giting/core/commands.py
giting/core/config.py
giting/core/fs_ops.py
giting/core/git_ops.py
giting/core/ignore_files.py
giting/core/shell_ops.py
giting/interactive/__init__.py
giting/interactive/display.py
giting/interactive/interact.py
giting-0.0.5.dist-info/LICENSE
giting-0.0.5.dist-info/METADATA
giting-0.0.5.dist-info/WHEEL
giting-0.0.5.dist-info/entry_points.txt
giting-0.0.5.dist-info/top_level.txt
giting-0.0.5.dist-info/RECORD
